argparse_app/__init__.py
argparse_app/app.py
argparse_app/version.py
argparse_app-0.0.1.dist-info/LICENSE
argparse_app-0.0.1.dist-info/METADATA
argparse_app-0.0.1.dist-info/WHEEL
argparse_app-0.0.1.dist-info/top_level.txt
argparse_app-0.0.1.dist-info/RECORD
